onapsmsclient/__init__.py
onapsmsclient-0.0.4.dist-info/DESCRIPTION.rst
onapsmsclient-0.0.4.dist-info/METADATA
onapsmsclient-0.0.4.dist-info/RECORD
onapsmsclient-0.0.4.dist-info/WHEEL
onapsmsclient-0.0.4.dist-info/metadata.json
onapsmsclient-0.0.4.dist-info/top_level.txt
