Metadata-Version: 2.0
Name: onapsmsclient
Version: 0.0.4
Summary: ONAP python SMS client library
Home-page: https://gerrit.onap.org/r/gitweb?p=aaf%2Fsms.git;a=summary
Author: Kiran Kamineni
Author-email: kiran.k.kamineni@intel.com
License: Apache 2
Keywords: secret,consul,onap
Platform: all
Classifier: Intended Audience :: Developers
Classifier: Programming Language :: Python :: 2.7
Classifier: Programming Language :: Python :: 3.6
Requires-Dist: requests (>=2.7.0)
Requires-Dist: urllib3 (>=1.22)
